{
  "hymn_number": 148,
  "title": "Many and Great, O God",
  "lyrics": [
    {
      "page_name": "Verse 1",
      "text": "Many and great, O God, are thy things,\nMaker of earth and sky.\nThy hands have set the heavens with stars;\n<br>thy fingers spread the mountains and plains.\nLo, at thy word the waters were formed;\ndeep seas obey thy voice."
    },
    {
      "page_name": "Verse 2",
      "text": "Grant unto us communion with thee,\nthou star abiding one;\ncome unto us and dwell with us;\n<br>with thee are found the gifts of life.\nBless us with life that has no end,\neternal life with thee."
    }
  ],
  "hymnal": "umh",
  "author": "Joseph R. Renville (ca. 1846)",
  "composer": "",
  "tune_name": "LACQUIPARLE",
  "text_copyright": "",
  "tune_copyright": "Harm. © 1986 G.I.A. Publications, Inc."
}